<Game>
	<Name>FIFA Soccer 97 (USA) (En,Fr,De,Es,It,Sv)</Name>
	<plot>One of the early FIFA football games. It was released for the Genesis, SNES, Saturn, PlayStation and the PC. It was the first FIFA game to include polygonal players. In previous games 2D sprites had been used. It was also the first FIFA game to include a 5-a-side indoor football arena to compete in.David Ginola (a Newcastle United winger) featured on the cover of the European version's, and Bebeto (a Brazilian Striker) was on the cover for the American and Asian versions of the game.The first Nintendo 64 FIFA game FIFA 64 was based on this game.Features:Fifa 97 is the first game in the series to use polygonal players, as previously the games featured 2D players. Fifa 97 continues to use the virtual stadium system which was introduced in Fifa 96. 			</plot>
	<releasedate>20/12/1996</releasedate>
	<genre>Sports</genre>
	<Developer>Electronic Arts, Inc.</Developer>
	<nplayers>1-2 Alt</nplayers>
	<rating>0</rating>
	<VideoURL>h0N08d81sSM</VideoURL>
	<thegamesdb_id>3611</thegamesdb_id>
	<gamefaqs_url>http://www.gamefaqs.com/snes/588328-fifa-soccer-97</gamefaqs_url>
	<mobygames_url>http://www.mobygames.com/game/snes/fifa-soccer-97_</mobygames_url>
	<giantbomb_url>http://www.giantbomb.com/fifa-soccer-97/3030-3383/</giantbomb_url>
	<boxart1>http://i.imgur.com/J0neMm8.jpg</boxart1>
	<boxart2>http://i.imgur.com/ghnGfOL.png</boxart2>
	<boxart3>http://i.imgur.com/MBnuRjh.jpg</boxart3>
	<boxart4>http://i.imgur.com/fU7lDaX.jpg</boxart4>
	<snapshot1>http://i.imgur.com/D7lvpu3.gif</snapshot1>
	<snapshot2>http://i.imgur.com/yCD0OFp.gif</snapshot2>
	<snapshot3>http://i.imgur.com/SsnwIL7.gif</snapshot3>
	<snapshot4>http://i.imgur.com/F5YFEiw.gif</snapshot4>
	<snapshot5>http://i.imgur.com/rbb3KBJ.gif</snapshot5>
	<snapshot6>http://i.imgur.com/2yoEM8m.gif</snapshot6>
	<snapshot7>http://i.imgur.com/gwr2AWV.gif</snapshot7>
	<snapshot8>http://i.imgur.com/kFotx8y.gif</snapshot8>
	<snapshot9>http://i.imgur.com/7JBboaK.gif</snapshot9>
	<snapshot10>http://i.imgur.com/TLy1ygW.gif</snapshot10>
	<fanart1>http://i.imgur.com/JIP0Do1.jpg</fanart1>
	<banner1>http://i.imgur.com/GIblznP.png</banner1>
	<clearlogo1>http://i.imgur.com/0ad0DSI.png</clearlogo1>
	<clearlogo2>http://i.imgur.com/PZHDp8a.png</clearlogo2>
	<Notes>You pulled them through 4 exhibitions, 38 league matches and 5 cup games. Tonight, 76,000 chanting soccer disciples have gathered to watch you carry their team to the promised land. You have their faith. Now prove you deserve it.</Notes>
	<boxart5>http://images.launchbox-app.com/7f7277e6-3264-446a-8cb1-33dc8ced926d.png</boxart5>
	<boxart6>http://images.launchbox-app.com/188072c5-f646-4753-9a28-4e6b0e2fa858.jpg</boxart6>
	<clearlogo3>http://images.launchbox-app.com/c00ad126-5c2b-4db1-a23b-975efe3bc308.png</clearlogo3>
	<clearlogo4>http://images.launchbox-app.com/741ee655-ee1a-494f-a00f-a6d0c997aee8.png</clearlogo4>
	<snapshot11>http://images.launchbox-app.com/3b8c05d0-337c-484d-a566-b5521a506f60.png</snapshot11>
	<snapshot12>http://images.launchbox-app.com/1f2d54c3-0a0b-459c-9ef4-b229c299dafe.png</snapshot12>
	<ESRB>E - Everyone</ESRB>
	<Publisher>Electronic Arts</Publisher>
</game>