<Game>
	<Name>SD Kidou Senshi Gundam 2 (Japan)</Name>
	<plot>Overview:SD Kidou Senshi Gundam 2 is a shoot 'em up game featuring characters from the Gundam universe in a super deformed format. It is the sequel to the Super Famicom game SD Kidou Senshi Gundam: V Sakusen Shidou. The player can select between three SD Gundam characters to play as, including the previous game's Knight Gundam.The game also has both co-operative and competitive two-player modes.	</plot>
	<releasedate>23/9/1993</releasedate>
	<genre>Action, Miscellaneous</genre>
	<Developer>TOSE</Developer>
	<nplayers>1-2 Co-Op</nplayers>
	<rating>8.0</rating>
	<gamefaqs_url>http://www.gamefaqs.com/snes/565617-sd-gundam-2</gamefaqs_url>
	<giantbomb_url>http://www.giantbomb.com/sd-kidou-senshi-gundam-2/3030-31322/</giantbomb_url>
	<boxart1>http://i.imgur.com/aCAPN3T.jpg</boxart1>
	<boxart2>http://i.imgur.com/fICyKiD.jpg</boxart2>
	<snapshot1>http://i.imgur.com/loPqhy7.jpg</snapshot1>
	<snapshot2>http://i.imgur.com/MGZ91Cg.jpg</snapshot2>
	<snapshot3>http://i.imgur.com/OwjPJPW.jpg</snapshot3>
	<snapshot4>http://i.imgur.com/WeVhx7C.jpg</snapshot4>
	<snapshot5>http://i.imgur.com/T9hC4Um.jpg</snapshot5>
	<snapshot6>http://i.imgur.com/a6RwIuQ.jpg</snapshot6>
	<snapshot7>http://i.imgur.com/E9m6Wlx.jpg</snapshot7>
	<snapshot8>http://i.imgur.com/U4KSJ06.jpg</snapshot8>
	<snapshot9>http://i.imgur.com/H8VyZSm.jpg</snapshot9>
	<snapshot10>http://i.imgur.com/BCxZZVM.jpg</snapshot10>
	<banner1>http://i.imgur.com/M33d4Ma.gif</banner1>
	<clearlogo1>http://i.imgur.com/w5b6qNF.png</clearlogo1>
	<Notes>SD Kidou Senshi Gundam 2 is a shoot 'em up game featuring characters from the Gundam universe in a super deformed format. It is the sequel to the Super Famicom game SD Kidou Senshi Gundam: V Sakusen Shidou. The player can select between three SD Gundam characters to play as, including the previous game's Knight Gundam. The game also has both co-operative and competitive two-player modes.</Notes>
	<boxart3>http://images.launchbox-app.com/ee431552-30fd-4f0b-ae52-ba30afbbf3c6.png</boxart3>
	<clearlogo2>http://images.launchbox-app.com/0f86f60f-b87e-4b7f-b209-fdf2f27d0021.png</clearlogo2>
	<Publisher>Angel (BANDAI)</Publisher>
</game>