<Game>
	<Name>Spider-Man & Venom- Maximum Carnage</Name>
	<ReleaseDate>1994-09-04T00:00:00-07:00</ReleaseDate>
	<Plot>Only one maniacal madman can force Spider-Man to unite with his sinister, arch-nemesis Venom’: CARNAGE’! His deadly rampage is tearing New York City apart! Only wild web-slinging maneuvers, crushing combat moves and Super Hero’ allies can save the city from total obliteration. It's maximum mayhem! It's Maximum Carnage’! Paint the town red!</Plot>
	<nPlayers>1</nPlayers>
	<VideoURL>b4Li0uOSR58</VideoURL>
	<1>http://images.launchbox-app.com/2ecab40b-fa18-4a39-ac01-9aeb4639d049.png</1>
	<boxback1>http://images.launchbox-app.com/59949438-dd9f-48f7-94b6-151ea17c3d65.jpg</boxback1>
	<boxart1>http://images.launchbox-app.com/c549fc4d-9e07-4b2f-9bb9-7e255935d4d2.jpg</boxart1>
	<clearlogo1>http://images.launchbox-app.com/6bdb6b6c-cb9c-4267-8d6f-fe52a0363d1a.png</clearlogo1>
	<fanart1>http://images.launchbox-app.com/f5bedad2-6e9b-47c4-a644-069056b88db6.png</fanart1>
	<fanart2>http://images.launchbox-app.com/30dd9124-6c61-4da1-a0d0-63c9059da463.png</fanart2>
	<fanart3>http://images.launchbox-app.com/006f3304-732c-45af-bab8-1a38871e64ef.jpg</fanart3>
	<snapshot1>http://images.launchbox-app.com/04111e7b-9630-4a0d-8f9c-4d99bfabbd67.png</snapshot1>
	<snapshot2>http://images.launchbox-app.com/590cbb7d-e9c2-4aa6-80ce-b7680eab00cf.png</snapshot2>
	<Rating>4</Rating>
	<WikipediaURL>https://en.wikipedia.org/wiki/Spider-Man_and_Venom:_Maximum_Carnage</WikipediaURL>
	<ESRB>Not Rated</ESRB>
	<Genre>Action</Genre>
	<Developer>Software Creations</Developer>
	<Publisher>LJN</Publisher>
</game>