<Game>
	<Name>Super Conflict- The Mideast</Name>
	<ReleaseDate>1993-01-01T00:00:00-08:00</ReleaseDate>
	<Plot>Super Conflict: The Mideast is a strategy game that compares itself to a game of chess: there are two sides (Blue or Red) who must destroy the opposing force's Flag Unit. (In the fifth skill level, there is also a Flag Ship, and the game is lost if either one is destroyed.) Scenarios are laid on on a hexagonal grid, and each space has its own terrain type and can be occupied by one unit. You move your units around and attack enemy units in adjacent hexagons. There are also cities, airports, and shipyards, which you can occupy and use for your own purposes (ie. to repair a unit). Depending on the skill level or scenario you can also construct factories to produce additional units.</Plot>
	<nPlayers>2</nPlayers>
	<1>http://images.launchbox-app.com/49169af9-0cf6-4267-9f2a-7879758bc3ea.png</1>
	<boxart1>http://images.launchbox-app.com/884b97bd-7f54-4499-b61f-9359e35d8ec8.png</boxart1>
	<boxart2>http://images.launchbox-app.com/9b82167e-68e9-4008-adf9-93924a3d15cd.png</boxart2>
	<clearlogo1>http://images.launchbox-app.com/3f0507c0-4c59-4581-b176-6ebd2acca7ad.png</clearlogo1>
	<Rating>1</Rating>
	<Genre>Strategy</Genre>
	<Developer>Vic Tokai</Developer>
	<Publisher>Vertigo</Publisher>
</game>