<Game>
	<Name>Cool Herders</Name>
	<ReleaseDate>2005-12-15T00:00:00-08:00</ReleaseDate>
	<Plot>Cool Herders is an addictive 2D multiplayer game that pits you against up to three friends in a game that can only be described as "Cool." Your goal is to collect the most sheep in a round, either by herding them yourself or by bashing your opponent and stealing his or her sheep! On top of the multiplayer fun, story mode will put you in the shoes of Zeus as he makes his way through level after level of challenges to get his herd back from the evil clutches of Iskur. The going won't be easy ? Zeus will have to travel far away from his homeland of New Zealand to complete challenges and compete against herders in various locations before taking on Iskur himself in a battle to restore peace in the pasture! Will you and Zeus with the day, or will Iskur horde the herd for himself?</Plot>
	<nPlayers>4</nPlayers>
	<boxart1>http://images.launchbox-app.com/5fd05d81-ca44-4dc6-a058-0f908badeb22.jpg</boxart1>
	<clearlogo1>http://images.launchbox-app.com/27daf447-cd46-4d1c-82a1-1ef993a364b4.png</clearlogo1>
	<Rating>3.5</Rating>
	<Genre>Action; Adventure</Genre>
	<Developer>Avalanche Software</Developer>
	<Publisher>THQ</Publisher>
</game>