<Game>
	<Name>2K Sports - Major League Baseball 2K7 (USA)</Name>
	<plot>It's a whole new ballgame. Major League Baseball 2K7 redefines the pure baseball video game experience with true, Next-Gen details, all-new throwing mechanics and a revolutionary presentation system.http://www.gamefaqs.com/portable/gbadvance/home/938002.html</plot>
	<releasedate>20/1/2007</releasedate>
	<genre>Sports</genre>
	<Developer>2K Sports</Developer>
	<rating>1.5</rating>
	<ESRB>E - Everyone</ESRB>
	<VideoURL>btZPlAIKU5U</VideoURL>
	<thegamesdb_id>15855</thegamesdb_id>
	<gamefaqs_url>http://www.gamefaqs.com/gba/938002-major-league-baseball-2k7</gamefaqs_url>
	<giantbomb_url>http://www.giantbomb.com/major-league-baseball-2k7/3030-21255/</giantbomb_url>
	<boxart1>https://cdn.thegamesdb.net/images/original/boxart/front/15855-1.jpg</boxart1>
	<boxart2>http://static.giantbomb.com/uploads/scale_large/0/56/230184-936391_81532_back.jpg</boxart2>
	<snapshot1>http://img.gamefaqs.net/screens/b/1/e/gfs_84209_1_1.jpg</snapshot1>
	<snapshot2>http://img.gamefaqs.net/screens/1/c/e/gfs_84209_1_2.jpg</snapshot2>
	<snapshot3>http://img.gamefaqs.net/screens/8/7/e/gfs_84209_1_3.jpg</snapshot3>
	<snapshot4>http://img.gamefaqs.net/screens/4/6/e/gfs_84209_1_4.jpg</snapshot4>
	<snapshot5>http://img.gamefaqs.net/screens/d/d/e/gfs_84209_1_5.jpg</snapshot5>
</game>