<Game>
	<Name>Mermaid Melody - Pichi Pichi Pitch (Japan)</Name>
	<plot>Mermaid Melody: Pichi Pichi Pitch is a Miscellaneous game, developed and published by Konami,which was released in Japan in 2003.</plot>
	<releasedate>9/10/2003</releasedate>
	<genre>Miscellaneous, Rhythm, Music</genre>
	<Developer>Konami</Developer>
	<gamefaqs_url>http://www.gamefaqs.com/gba/918716-mermaid-melody-pichi-pichi-pitch</gamefaqs_url>
	<boxart1>http://img.gamefaqs.net/box/3/1/8/313318_front.jpg</boxart1>
	<snapshot1>http://img.gamefaqs.net/screens/e/c/a/gfs_25432_1_1.jpg</snapshot1>
	<snapshot2>http://img.gamefaqs.net/screens/4/1/a/gfs_25432_1_2.jpg</snapshot2>
	<snapshot3>http://img.gamefaqs.net/screens/4/5/7/gfs_25432_2_1.jpg</snapshot3>
	<snapshot4>http://img.gamefaqs.net/screens/e/8/7/gfs_25432_2_2.jpg</snapshot4>
	<snapshot5>http://img.gamefaqs.net/screens/7/3/7/gfs_25432_2_3.jpg</snapshot5>
</game>