<Game>
	<Name>Pokémon Cloud White</Name>
	<ReleaseDate>2015</ReleaseDate>
	<Plot>Pokémon Cloud White is another Pokémon Hack based mainly on Pokemon Fire Red. The story of Cloud White takes place right after the original story of FireRed. A whole new adventure is waiting for you.</Plot>
	<boxart1>http://images.launchbox-app.com/5d093091-636b-4417-a4c3-b6772e340850.jpg</boxart1>
	<ESRB>E - Everyone</ESRB>
	<Genre>Adventure; Role-Playing</Genre>
	<Developer>Shogun</Developer>
	<Publisher>Nintendo</Publisher>
</game>