<Game>
	<Name>Sports Illustrated for Kids - Baseball (USA)</Name>
	<plot>Step up to the plate with Sports Illustrated For Kids Baseball and see if you have what it takes to get to the majors. Choose your team, select your starting line-up and step onto the field for hard-hitting baseball action. Gain experience to build up your players' strength, speed and stamina and soon they'll be cranking balls out of the yard. Manage to take the championship and you'll move one step closer to the majors where the competition becomes truly intense!http://www.gamefaqs.com/portable/gbadvance/home/528589.html</plot>
	<releasedate>20/1/2001</releasedate>
	<genre>Sports</genre>
	<Developer>Bam Entertainment</Developer>
	<rating>6.8</rating>
	<ESRB>E - Everyone</ESRB>
	<thegamesdb_id>22307</thegamesdb_id>
	<gamefaqs_url>http://www.gamefaqs.com/gba/528589-sports-illustrated-for-kids-baseball</gamefaqs_url>
	<boxart1>https://cdn.thegamesdb.net/images/original/boxart/front/22307-1.jpg</boxart1>
	<boxart2>http://img.gamefaqs.net/box/9/9/8/14998_back.jpg</boxart2>
	<snapshot1>http://img.gamefaqs.net/screens/4/8/8/gfs_44474_1_1.jpg</snapshot1>
	<snapshot2>http://img.gamefaqs.net/screens/e/5/8/gfs_44474_1_2.jpg</snapshot2>
	<snapshot3>http://img.gamefaqs.net/screens/7/e/8/gfs_44474_1_3.jpg</snapshot3>
	<snapshot4>http://img.gamefaqs.net/screens/b/f/8/gfs_44474_1_4.jpg</snapshot4>
	<snapshot5>http://img.gamefaqs.net/screens/e/1/5/gfs_44474_2_1.jpg</snapshot5>
	<Notes>Sports Illustrated for Kids Baseball will combine extensive player development, player trading, team management and arcade-style play into a unified system of game play. Kids can assemble a team, name their team, choose a team uniform style and then train their players to make them better and advance through the leagues. Plus, two friends can link up their Game Boy Advances for hours of gaming fun - the only baseball game on the GBA that offers multiplayer capabilities!</Notes>
	<boxart3>http://images.launchbox-app.com/abd00cd4-3f34-4ac4-8cdc-fb835f3a7a0f.jpg</boxart3>
	<Publisher>Bam Entertainment</Publisher>
</game>