<Game>
	<Name>Suite Life of Zack & Cody, The - Tipton Caper (USA) (En,Fr)</Name>
	<plot>The Suite Life of Zack &amp; Cody: Tipton Caper is an action game with light puzzles. In the game, the player will independently control both twins, Zack and Cody. As in the television series, Zack and Cody manage to get themselves into outrageous situations which they then have to fix.http://www.gamefaqs.com/portable/gbadvance/home/933946.html</plot>
	<releasedate>20/1/2006</releasedate>
	<genre>Action</genre>
	<Developer>Buena Vista Games</Developer>
	<rating>4.0</rating>
	<thegamesdb_id>27912</thegamesdb_id>
	<gamefaqs_url>http://www.gamefaqs.com/gba/933946-the-suite-life-of-zack-and-cody-tipton-caper</gamefaqs_url>
	<giantbomb_url>http://www.giantbomb.com/the-suite-life-of-zack-cody-tipton-caper/3030-24153/</giantbomb_url>
	<boxart1>https://cdn.thegamesdb.net/images/original/boxart/front/27912-1.jpg</boxart1>
	<snapshot1>http://img.gamefaqs.net/screens/e/a/4/gfs_77128_1_1.jpg</snapshot1>
	<snapshot2>http://img.gamefaqs.net/screens/4/7/4/gfs_77128_1_2.jpg</snapshot2>
	<snapshot3>http://img.gamefaqs.net/screens/d/c/4/gfs_77128_1_3.jpg</snapshot3>
	<snapshot4>http://img.gamefaqs.net/screens/1/d/4/gfs_77128_1_4.jpg</snapshot4>
	<snapshot5>http://img.gamefaqs.net/screens/8/6/4/gfs_77128_1_5.jpg</snapshot5>
</game>