<Game>
	<Name>Super Mario Advance 4 - Super Mario 3 + Mario Brothers (Japan) (Rev 1)</Name>
	<plot>Mario hasn't even had a chance to savor his victory in the original Super Mario Advance, and already he's back for more in Super Mario World: Super Mario Advance 2.This game is a re-creation of the Super NES classic Super Mario World, featuring every last secret exit and all 74 levels of platform-jumping action.Once again, Princess Peach has been kidnapped by the ever-diabolical Bowser, and Mario and Luigi set out on a massive adventure to rescue her.As either Mario or Luigi, you'll solve puzzles, shoot fireballs, fly, and discover the hidden secrets in Dinosaur Island.</plot>
	<releasedate>9/2/2002</releasedate>
	<genre>Action, Platform, 2D</genre>
	<Developer>Nintendo</Developer>
	<nplayers>1</nplayers>
	<rating>9.1</rating>
	<ESRB>E - Everyone</ESRB>
	<VideoURL>xzArNQRCxO0</VideoURL>
	<thegamesdb_id>2350</thegamesdb_id>
	<gamefaqs_url>http://www.gamefaqs.com/gba/472572-super-mario-world-super-mario-advance-2</gamefaqs_url>
	<boxart1>https://cdn.thegamesdb.net/images/original/boxart/front/2350-1.jpg</boxart1>
	<boxback1>https://cdn.thegamesdb.net/images/original/boxart/back/2350-1.jpg</boxback1>
	<snapshot1>http://img.gamefaqs.net/screens/9/e/3/gfs_21798_1_1.jpg</snapshot1>
	<snapshot2>http://img.gamefaqs.net/screens/d/a/0/gfs_21799_1_1.jpg</snapshot2>
	<snapshot3>http://img.gamefaqs.net/screens/7/7/0/gfs_21799_1_2.jpg</snapshot3>
	<snapshot4>http://img.gamefaqs.net/screens/3/7/3/gfs_50847_1_1.jpg</snapshot4>
	<snapshot5>http://img.gamefaqs.net/screens/9/a/3/gfs_50847_1_2.jpg</snapshot5>
	<fanart1>https://cdn.thegamesdb.net/images/original/fanart/2350-1.jpg</fanart1>
	<fanart2>https://cdn.thegamesdb.net/images/original/fanart/2350-2.jpg</fanart2>
	<fanart3>https://cdn.thegamesdb.net/images/original/fanart/2350-3.jpg</fanart3>
	<fanart4>https://cdn.thegamesdb.net/images/original/fanart/2350-4.jpg</fanart4>
	<fanart5>https://cdn.thegamesdb.net/images/original/fanart/2350-5.jpg</fanart5>
	<fanart6>https://cdn.thegamesdb.net/images/original/fanart/2350-6.jpg</fanart6>
	<fanart7>https://cdn.thegamesdb.net/images/original/fanart/2350-7.jpg</fanart7>
	<fanart8>https://cdn.thegamesdb.net/images/original/fanart/2350-8.jpg</fanart8>
	<banner1>https://cdn.thegamesdb.net/banners/graphical/2350-g.jpg</banner1>
	<clearlogo1>https://cdn.thegamesdb.net/images/original/clearlogo/2350.png</clearlogo1>
</game>